pyhbasecli/HBase.py
pyhbasecli/__init__.py
pyhbasecli/hbase/THBaseService.py
pyhbasecli/hbase/__init__.py
pyhbasecli/hbase/constants.py
pyhbasecli/hbase/ttypes.py
pyhbasecli-0.0.2.dist-info/LICENSE
pyhbasecli-0.0.2.dist-info/METADATA
pyhbasecli-0.0.2.dist-info/WHEEL
pyhbasecli-0.0.2.dist-info/top_level.txt
pyhbasecli-0.0.2.dist-info/RECORD
