Metadata-Version: 2.1
Name: pyhbasecli
Version: 0.0.2
Summary: 基于thrift2的hbase客户端
Author: hsz
Author-email: hsz1273327@gmail.com
License: MIT License
Keywords: hbase,thrift
Classifier: License :: OSI Approved :: MIT License
Classifier: Programming Language :: Python :: 3.6
Classifier: Programming Language :: Python :: 3.7
Classifier: Programming Language :: Python :: 3.8
Classifier: Programming Language :: Python :: 3.9
License-File: LICENSE
Requires-Dist: thrift (>=0.16.0)
